LICENSE
MANIFEST.in
README
README.md
setup.cfg
setup.py
pyiArduinoI2Ctds/__init__.py
pyiArduinoI2Ctds/iarduino_I2C_PI.cpp
pyiArduinoI2Ctds/iarduino_I2C_PI.h
pyiArduinoI2Ctds/iarduino_I2C_TDS.cpp
pyiArduinoI2Ctds/iarduino_I2C_TDS.h
pyiArduinoI2Ctds/iarduino_I2C_TDS.pxd
pyiArduinoI2Ctds/pyiArduinoI2Ctds.cpp
pyiArduinoI2Ctds/pyiArduinoI2Ctds.pyx
pyiArduinoI2Ctds/setup.py
pyiArduinoI2Ctds.egg-info/PKG-INFO
pyiArduinoI2Ctds.egg-info/SOURCES.txt
pyiArduinoI2Ctds.egg-info/dependency_links.txt
pyiArduinoI2Ctds.egg-info/top_level.txt
pyiArduinoI2Ctds/cpp/FindDevices.cpp
pyiArduinoI2Ctds/cpp/NewAddress.cpp
pyiArduinoI2Ctds/cpp/Serial.h
pyiArduinoI2Ctds/cpp/getData.cpp
pyiArduinoI2Ctds/cpp/getSettings.cpp
pyiArduinoI2Ctds/cpp/main.cpp
pyiArduinoI2Ctds/cpp/setCalibration.cpp
pyiArduinoI2Ctds/examples/FindDevices.py
pyiArduinoI2Ctds/examples/getData.py
pyiArduinoI2Ctds/examples/getSettings.py
pyiArduinoI2Ctds/examples/newAddress.py
pyiArduinoI2Ctds/examples/setCalibration.py
pyiArduinoI2Ctds/examples/setSettings.py